tuyaha/__init__.py
tuyaha/tuyaapi.py
tuyaha/devices/__init__.py
tuyaha/devices/base.py
tuyaha/devices/climate.py
tuyaha/devices/cover.py
tuyaha/devices/factory.py
tuyaha/devices/fan.py
tuyaha/devices/light.py
tuyaha/devices/lock.py
tuyaha/devices/remote.py
tuyaha/devices/scene.py
tuyaha/devices/switch.py
tuyaha-0.0.11.dist-info/LICENSE
tuyaha-0.0.11.dist-info/METADATA
tuyaha-0.0.11.dist-info/WHEEL
tuyaha-0.0.11.dist-info/top_level.txt
tuyaha-0.0.11.dist-info/RECORD
