Metadata-Version: 2.1
Name: tuyaha
Version: 0.0.11
Summary: A Python library that implements a Tuya API endpoint that was specially designed for Home Assistant
Home-page: https://github.com/PaulAnnekov/tuyaha
Author: Pavlo Annekov and original Tuya authors
Author-email: paul.annekov@gmail.com
License: MIT
Platform: UNKNOWN
Classifier: Programming Language :: Python :: 3
Classifier: License :: OSI Approved :: MIT License
Classifier: Operating System :: OS Independent
Requires-Dist: requests
